{
  "version": "1",
  "cognitoConfig": {
    "identityPoolName": "lineclone6268a6de_identitypool_6268a6de",
    "allowUnauthenticatedIdentities": false,
    "resourceNameTruncated": "linecl6268a6de",
    "userPoolName": "lineclone6268a6de_userpool_6268a6de",
    "autoVerifiedAttributes": [
      "email"
    ],
    "mfaConfiguration": "OFF",
    "mfaTypes": [
      "SMS Text Message"
    ],
    "smsAuthenticationMessage": "Your authentication code is {####}",
    "smsVerificationMessage": "Your verification code is {####}",
    "emailVerificationSubject": "Your verification code",
    "emailVerificationMessage": "Your verification code is {####}",
    "defaultPasswordPolicy": true,
    "passwordPolicyMinLength": 8,
    "passwordPolicyCharacters": [
      "Requires Lowercase",
      "Requires Uppercase",
      "Requires Numbers"
    ],
    "requiredAttributes": [
      "email",
      "name",
      "preferred_username"
    ],
    "aliasAttributes": [
      "email",
      "preferred_username"
    ],
    "userpoolClientGenerateSecret": false,
    "userpoolClientRefreshTokenValidity": 30,
    "userpoolClientWriteAttributes": [
      "email"
    ],
    "userpoolClientReadAttributes": [
      "email"
    ],
    "userpoolClientLambdaRole": "LineCl6268a6de_userpoolclient_lambda_role",
    "userpoolClientSetAttributes": false,
    "sharedId": "6268a6de",
    "resourceName": "LineCloneUserpool",
    "authSelections": "identityPoolAndUserPool",
    "useDefault": "manual",
    "thirdPartyAuth": true,
    "authProviders": [],
    "userPoolGroups": false,
    "adminQueries": false,
    "triggers": {},
    "hostedUI": false,
    "userPoolGroupList": [],
    "serviceName": "Cognito",
    "usernameCaseSensitive": false,
    "useEnabledMfas": true
  }
}